sympy_slider/__init__.py
sympy_slider/slider.py
sympy_slider-0.0.3.dist-info/LICENSE.TXT
sympy_slider-0.0.3.dist-info/METADATA
sympy_slider-0.0.3.dist-info/WHEEL
sympy_slider-0.0.3.dist-info/top_level.txt
sympy_slider-0.0.3.dist-info/RECORD
