Metadata-Version: 2.1
Name: sympy-slider
Version: 0.0.3
Summary: Make slider from sympy expression and params
Home-page: https://github.com/bfichera/sympy-slider
Author: Bryan Fichera
Author-email: bfichera@mit.edu
Classifier: Programming Language :: Python :: 3
Classifier: License :: OSI Approved :: MIT License
Classifier: Operating System :: OS Independent
License-File: LICENSE.TXT
Requires-Dist: sympy
Requires-Dist: numpy
Requires-Dist: matplotlib
